README.rst
setup.py
presentation_api_controller.egg-info/PKG-INFO
presentation_api_controller.egg-info/SOURCES.txt
presentation_api_controller.egg-info/dependency_links.txt
presentation_api_controller.egg-info/not-zip-safe
presentation_api_controller.egg-info/top_level.txt
presentation_controller/__init__.py
presentation_controller/controller.py
test/__init__.py
test/pserver.py