Metadata-Version: 1.0
Name: presentation-api-controller
Version: 0.0.3
Summary: Presentation API Controller for MCTS
Home-page: https://github.com/askeing/presentation_api_controller
Author: Askeing Yen
Author-email: askeing@gmail.com
License: UNKNOWN
Keywords: mozilla b2g firefoxos fxos MCTS
Platform: UNKNOWN
